pytracktry/__init__.py
pytracktry/tracker.py
pytracktry-0.1.dist-info/LICENSE
pytracktry-0.1.dist-info/METADATA
pytracktry-0.1.dist-info/WHEEL
pytracktry-0.1.dist-info/top_level.txt
pytracktry-0.1.dist-info/RECORD
