Metadata-Version: 2.1
Name: pytracktry
Version: 0.1
Summary: A python wrapper for the TrackTry API
Home-page: https://github.com/concentricc/pytracktry
Author: Concentricc
Author-email: Concentricc@gmail.com
License: UNKNOWN
Platform: UNKNOWN
Classifier: Programming Language :: Python :: 3
Classifier: License :: OSI Approved :: MIT License
Classifier: Operating System :: OS Independent
Requires-Dist: aiohttp
Requires-Dist: async-timeout
